aliyunsdkappstream_center/__init__.py
aliyunsdkappstream_center/request/__init__.py
aliyunsdkappstream_center/request/v20210901/ApproveOtaTaskRequest.py
aliyunsdkappstream_center/request/v20210901/AuthorizeInstanceGroupRequest.py
aliyunsdkappstream_center/request/v20210901/CancelOtaTaskRequest.py
aliyunsdkappstream_center/request/v20210901/CreateAppInstanceGroupRequest.py
aliyunsdkappstream_center/request/v20210901/DeleteAppInstanceGroupRequest.py
aliyunsdkappstream_center/request/v20210901/DeleteAppInstancesRequest.py
aliyunsdkappstream_center/request/v20210901/GetAppInstanceGroupRequest.py
aliyunsdkappstream_center/request/v20210901/GetConnectionTicketRequest.py
aliyunsdkappstream_center/request/v20210901/GetOtaTaskByTaskIdRequest.py
aliyunsdkappstream_center/request/v20210901/GetResourcePriceRequest.py
aliyunsdkappstream_center/request/v20210901/GetResourceRenewPriceRequest.py
aliyunsdkappstream_center/request/v20210901/ListAppInstanceGroupRequest.py
aliyunsdkappstream_center/request/v20210901/ListAppInstancesRequest.py
aliyunsdkappstream_center/request/v20210901/ListNodeInstanceTypeRequest.py
aliyunsdkappstream_center/request/v20210901/ListOtaTaskRequest.py
aliyunsdkappstream_center/request/v20210901/ListRegionsRequest.py
aliyunsdkappstream_center/request/v20210901/ListTenantConfigRequest.py
aliyunsdkappstream_center/request/v20210901/LogOffAllSessionsInAppInstanceGroupRequest.py
aliyunsdkappstream_center/request/v20210901/ModifyAppInstanceGroupAttributeRequest.py
aliyunsdkappstream_center/request/v20210901/ModifyNodePoolAttributeRequest.py
aliyunsdkappstream_center/request/v20210901/ModifyTenantConfigRequest.py
aliyunsdkappstream_center/request/v20210901/PageListAppInstanceGroupUserRequest.py
aliyunsdkappstream_center/request/v20210901/RenewAppInstanceGroupRequest.py
aliyunsdkappstream_center/request/v20210901/UnbindRequest.py
aliyunsdkappstream_center/request/v20210901/UpdateAppInstanceGroupImageRequest.py
aliyun_python_sdk_appstream_center-1.0.1.dist-info/LICENSE
aliyun_python_sdk_appstream_center-1.0.1.dist-info/METADATA
aliyun_python_sdk_appstream_center-1.0.1.dist-info/WHEEL
aliyun_python_sdk_appstream_center-1.0.1.dist-info/top_level.txt
aliyun_python_sdk_appstream_center-1.0.1.dist-info/RECORD
